falign/__init__.py
falign/__main__.py
falign/falign.py
fortran_align-0.0.7.dist-info/LICENSE
fortran_align-0.0.7.dist-info/METADATA
fortran_align-0.0.7.dist-info/WHEEL
fortran_align-0.0.7.dist-info/entry_points.txt
fortran_align-0.0.7.dist-info/top_level.txt
fortran_align-0.0.7.dist-info/RECORD
