Metadata-Version: 2.1
Name: fortran-align
Version: 0.0.7
Summary: Fortran comment alignment tool
Home-page: https://gitlab.com/TobiasRH/fortran-align
Author: Tobias R. Henle
Author-email: tobias@page23.de
License: UNKNOWN
Platform: UNKNOWN
Classifier: Programming Language :: Python :: 3
Classifier: License :: OSI Approved :: MIT License
Classifier: Operating System :: OS Independent
Requires-Python: >=3.6
